<?xml version="1.0" encoding="utf-8"?>
<Defs>
  <!-- Mer Race PawnKinds -->
  <PawnKindDef>
    <defName>BosmerCivilian</defName>
    <label>Bosmer</label>
    <race>Bosmer</race>
    <defaultFactionType>PlayerColony</defaultFactionType>
    <combatPower>75</combatPower>
    <backstoryCategories>
      <li>Civil</li>
      <li>Tribal</li>
    </backstoryCategories>
    <defaultOutfit>Clothes</defaultOutfit>
    <inventoryOptions>
      <li>
        <thingDef>MealSimple</thingDef>
        <count>3</count>
      </li>
    </inventoryOptions>
    <itemQuality>Normal</itemQuality>
    <forcedTraits>
      <li>BosmerForestWisdom</li>
    </forcedTraits>
    <allowedWorkTypes>
      <li>All</li>
    </allowedWorkTypes>
    <skills>
      <li>
        <skill>Shooting</skill>
        <level>6</level>
      </li>
      <li>
        <skill>Animals</skill>
        <level>3</level>
      </li>
      <li>
        <skill>Plants</skill>
        <level>3</level>
      </li>
    </skills>
  </PawnKindDef>

  <PawnKindDef>
    <defName>AltmerCivilian</defName>
    <label>Altmer</label>
    <race>Altmer</race>
    <defaultFactionType>PlayerColony</defaultFactionType>
    <combatPower>65</combatPower>
    <backstoryCategories>
      <li>Civil</li>
      <li>Tribal</li>
    </backstoryCategories>
    <defaultOutfit>Clothes</defaultOutfit>
    <inventoryOptions>
      <li>
        <thingDef>MealSimple</thingDef>
        <count>3</count>
      </li>
    </inventoryOptions>
    <itemQuality>Good</itemQuality>
    <forcedTraits>
      <li>AltmerMagicalAffinity</li>
    </forcedTraits>
    <allowedWorkTypes>
      <li>All</li>
    </allowedWorkTypes>
    <skills>
      <li>
        <skill>Intellectual</skill>
        <level>6</level>
      </li>
      <li>
        <skill>Artistic</skill>
        <level>3</level>
      </li>
      <li>
        <skill>Crafting</skill>
        <level>2</level>
      </li>
    </skills>
  </PawnKindDef>

  <PawnKindDef>
    <defName>OrsimerCivilian</defName>
    <label>Orsimer</label>
    <race>Orsimer</race>
    <defaultFactionType>PlayerColony</defaultFactionType>
    <combatPower>95</combatPower>
    <backstoryCategories>
      <li>Civil</li>
      <li>Tribal</li>
    </backstoryCategories>
    <defaultOutfit>Clothes</defaultOutfit>
    <inventoryOptions>
      <li>
        <thingDef>MealSimple</thingDef>
        <count>3</count>
      </li>
    </inventoryOptions>
    <itemQuality>Normal</itemQuality>
    <forcedTraits>
      <li>OrsimerFerocity</li>
    </forcedTraits>
    <allowedWorkTypes>
      <li>All</li>
    </allowedWorkTypes>
    <skills>
      <li>
        <skill>Melee</skill>
        <level>6</level>
      </li>
      <li>
        <skill>Crafting</skill>
        <level>4</level>
      </li>
      <li>
        <skill>Mining</skill>
        <level>3</level>
      </li>
    </skills>
  </PawnKindDef>
</Defs>