<?xml version="1.0" encoding="utf-8"?>
<Defs>

  <!-- House Redoran Gah-Julan Bonemould Armor -->
  <ThingDef ParentName="ArmorMakeableBase">
    <defName>Apparel_HouseRedoranArmor</defName>
    <label>House Redoran Gah-Julan bonemould armor</label>
    <description>The iconic Gah-Julan bonemould armor worn by House Redoran warriors. This traditional Dunmer armor is crafted from the hardened shells and bones of native creatures, providing excellent protection while maintaining mobility. The distinctive styling reflects House Redoran's martial heritage and their role as Morrowind's defender-warriors.</description>
    <graphicData>
      <texPath>Things/Pawn/Humanlike/Apparel/GreatHouses/Redoran/Redoran</texPath>
      <graphicClass>Graphic_Single</graphicClass>
    </graphicData>
    <costStuffCount>120</costStuffCount>
    <stuffCategories>
      <li>Metallic</li>
      <li>Woody</li>
    </stuffCategories>
    <thingCategories>
      <li>ApparelArmor</li>
    </thingCategories>
    <statBases>
      <WorkToMake>20000</WorkToMake>
      <MaxHitPoints>290</MaxHitPoints>
      <Mass>13</Mass>
      <Flammability>0.4</Flammability>
      <ArmorRating_Sharp>0.74</ArmorRating_Sharp>
      <ArmorRating_Blunt>0.38</ArmorRating_Blunt>
      <ArmorRating_Heat>0.42</ArmorRating_Heat>
      <Insulation_Cold>9</Insulation_Cold>
      <Insulation_Heat>3</Insulation_Heat>
      <EquipDelay>11</EquipDelay>
    </statBases>
    <equippedStatOffsets>
      <MoveSpeed>-0.06</MoveSpeed>
      <WorkSpeedGlobal>-0.06</WorkSpeedGlobal>
      <MeleeHitChance>0.06</MeleeHitChance>
      <ConstructionSpeed>0.08</ConstructionSpeed>
    </equippedStatOffsets>
    <apparel>
      <bodyPartGroups>
        <li>Torso</li>
        <li>Neck</li>
        <li>Shoulders</li>
        <li>Arms</li>
        <li>Legs</li>
      </bodyPartGroups>
      <wornGraphicPath>Things/Pawn/Humanlike/Apparel/GreatHouses/Redoran/Redoran</wornGraphicPath>
      <layers>
        <li>Middle</li>
      </layers>
      <tags>
        <li>IndustrialMilitaryBasic</li>
        <li>HouseRedoran</li>
      </tags>
      <defaultOutfitTags>
        <li>Soldier</li>
      </defaultOutfitTags>
    </apparel>
    <recipeMaker>
      <unfinishedThingDef>UnfinishedMetallicTechArmor</unfinishedThingDef>
      <researchPrerequisite>PlateArmor</researchPrerequisite>
      <skillRequirements>
        <Crafting>7</Crafting>
      </skillRequirements>
      <recipeUsers Inherit="False">
        <li>ElectricSmithy</li>
        <li>FueledSmithy</li>
      </recipeUsers>
    </recipeMaker>
  </ThingDef>

  <!-- House Redoran Master Helmet -->
  <ThingDef ParentName="ArmorMakeableBase">
    <defName>Apparel_HouseRedoranMasterHelmet</defName>
    <label>House Redoran Master helmet</label>
    <description>The unique ceremonial helmet worn by the leader of House Redoran. This masterwork piece of Gah-Julan bonemould armor features intricate decorations and superior craftsmanship, marking its wearer as the supreme commander of House Redoran's martial forces.</description>
    <graphicData>
      <texPath>Things/Pawn/Humanlike/Apparel/GreatHouses/Redoran/RedoranMasterHelm</texPath>
      <graphicClass>Graphic_Single</graphicClass>
    </graphicData>
    <costStuffCount>75</costStuffCount>
    <stuffCategories>
      <li>Metallic</li>
      <li>Woody</li>
    </stuffCategories>
    <thingCategories>
      <li>ApparelArmor</li>
    </thingCategories>
    <statBases>
      <WorkToMake>15000</WorkToMake>
      <MaxHitPoints>150</MaxHitPoints>
      <Mass>3.5</Mass>
      <Flammability>0.3</Flammability>
      <ArmorRating_Sharp>0.85</ArmorRating_Sharp>
      <ArmorRating_Blunt>0.45</ArmorRating_Blunt>
      <ArmorRating_Heat>0.45</ArmorRating_Heat>
      <Insulation_Cold>5</Insulation_Cold>
      <Insulation_Heat>2</Insulation_Heat>
      <EquipDelay>4</EquipDelay>
    </statBases>
    <equippedStatOffsets>
      <MeleeHitChance>0.08</MeleeHitChance>
      <SocialImpact>0.20</SocialImpact>
      <MentalBreakThreshold>-0.10</MentalBreakThreshold>
    </equippedStatOffsets>
    <apparel>
      <bodyPartGroups>
        <li>UpperHead</li>
        <li>FullHead</li>
      </bodyPartGroups>
      <wornGraphicPath>Things/Pawn/Humanlike/Apparel/GreatHouses/Redoran/RedoranMasterHelm</wornGraphicPath>
      <layers>
        <li>Overhead</li>
      </layers>
      <tags>
        <li>IndustrialMilitaryAdvanced</li>
        <li>HouseRedoran</li>
        <li>RedoranLeader</li>
      </tags>
      <defaultOutfitTags>
        <li>Soldier</li>
      </defaultOutfitTags>
    </apparel>
    <recipeMaker>
      <unfinishedThingDef>UnfinishedMetallicTechArmor</unfinishedThingDef>
      <researchPrerequisite>PlateArmor</researchPrerequisite>
      <skillRequirements>
        <Crafting>9</Crafting>
      </skillRequirements>
      <recipeUsers Inherit="False">
        <li>ElectricSmithy</li>
        <li>FueledSmithy</li>
      </recipeUsers>
    </recipeMaker>
  </ThingDef>

  <!-- House Hlaalu Armun-An Bonemould Armour -->
  <ThingDef ParentName="ArmorMakeableBase">
    <defName>Apparel_HouseHlaaluArmor</defName>
    <label>House Hlaalu Armun-An bonemould armour</label>
    <description>The traditional Armun-An bonemould armor worn by House Hlaalu warriors and guards. While House Hlaalu is known for diplomacy and trade, they are not defenseless. This practical armor combines the standard bonemould construction with decorative elements befitting Morrowind's most prosperous merchant house.</description>
    <graphicData>
      <texPath>Things/Pawn/Humanlike/Apparel/GreatHouses/Hlaalu/Hlaalu</texPath>
      <graphicClass>Graphic_Single</graphicClass>
    </graphicData>
    <costStuffCount>115</costStuffCount>
    <stuffCategories>
      <li>Metallic</li>
      <li>Woody</li>
    </stuffCategories>
    <thingCategories>
      <li>ApparelArmor</li>
    </thingCategories>
    <statBases>
      <WorkToMake>18000</WorkToMake>
      <MaxHitPoints>275</MaxHitPoints>
      <Mass>12</Mass>
      <Flammability>0.4</Flammability>
      <ArmorRating_Sharp>0.70</ArmorRating_Sharp>
      <ArmorRating_Blunt>0.35</ArmorRating_Blunt>
      <ArmorRating_Heat>0.40</ArmorRating_Heat>
      <Insulation_Cold>8</Insulation_Cold>
      <Insulation_Heat>3</Insulation_Heat>
      <EquipDelay>10</EquipDelay>
    </statBases>
    <equippedStatOffsets>
      <MoveSpeed>-0.05</MoveSpeed>
      <TradePriceImprovement>0.08</TradePriceImprovement>
      <NegotiationAbility>0.10</NegotiationAbility>
      <SocialImpact>0.12</SocialImpact>
    </equippedStatOffsets>
    <apparel>
      <bodyPartGroups>
        <li>Torso</li>
        <li>Neck</li>
        <li>Shoulders</li>
        <li>Arms</li>
        <li>Legs</li>
      </bodyPartGroups>
      <wornGraphicPath>Things/Pawn/Humanlike/Apparel/GreatHouses/Hlaalu/Hlaalu</wornGraphicPath>
      <layers>
        <li>Middle</li>
      </layers>
      <tags>
        <li>IndustrialMilitaryBasic</li>
        <li>HouseHlaalu</li>
      </tags>
      <defaultOutfitTags>
        <li>Soldier</li>
      </defaultOutfitTags>
    </apparel>
    <recipeMaker>
      <unfinishedThingDef>UnfinishedMetallicTechArmor</unfinishedThingDef>
      <researchPrerequisite>PlateArmor</researchPrerequisite>
      <skillRequirements>
        <Crafting>6</Crafting>
      </skillRequirements>
      <recipeUsers Inherit="False">
        <li>ElectricSmithy</li>
        <li>FueledSmithy</li>
      </recipeUsers>
    </recipeMaker>
  </ThingDef>

  <!-- House Telvanni Robes -->
  <ThingDef ParentName="ApparelMakeableBase">
    <defName>Apparel_HouseTelvanniRobes</defName>
    <label>House Telvanni robes</label>
    <description>Mystical robes worn by the sorcerers of House Telvanni. These flowing garments are woven with arcane patterns and shimmer with magical energy, providing both comfort for long study sessions and protection against magical threats.</description>
    <graphicData>
      <texPath>Things/Pawn/Humanlike/Apparel/GreatHouses/Telvanni/Telvanni</texPath>
      <graphicClass>Graphic_Single</graphicClass>
      <shaderType>CutoutComplex</shaderType>
    </graphicData>
    <costStuffCount>90</costStuffCount>
    <stuffCategories>
      <li>Fabric</li>
    </stuffCategories>
    <thingCategories>
      <li>Apparel</li>
    </thingCategories>
    <statBases>
      <WorkToMake>12000</WorkToMake>
      <MaxHitPoints>100</MaxHitPoints>
      <Mass>1.8</Mass>
      <Flammability>0.8</Flammability>
      <ArmorRating_Sharp>0.08</ArmorRating_Sharp>
      <ArmorRating_Blunt>0.04</ArmorRating_Blunt>
      <ArmorRating_Heat>0.25</ArmorRating_Heat>
      <Insulation_Cold>18</Insulation_Cold>
      <Insulation_Heat>12</Insulation_Heat>
      <EquipDelay>4</EquipDelay>
    </statBases>
    <equippedStatOffsets>
      <ResearchSpeed>0.20</ResearchSpeed>
      <GlobalLearningFactor>0.10</GlobalLearningFactor>
      <PsychicSensitivity>0.15</PsychicSensitivity>
      <MentalBreakThreshold>-0.05</MentalBreakThreshold>
    </equippedStatOffsets>
    <apparel>
      <bodyPartGroups>
        <li>Torso</li>
        <li>Neck</li>
        <li>Shoulders</li>
        <li>Arms</li>
        <li>Legs</li>
      </bodyPartGroups>
      <wornGraphicPath>Things/Pawn/Humanlike/Apparel/GreatHouses/Telvanni/Telvanni</wornGraphicPath>
      <layers>
        <li>Middle</li>
      </layers>
      <tags>
        <li>HouseTelvanni</li>
      </tags>
      <defaultOutfitTags>
        <li>Worker</li>
      </defaultOutfitTags>
    </apparel>
    <recipeMaker>
      <researchPrerequisite>ComplexClothing</researchPrerequisite>
      <skillRequirements>
        <Crafting>6</Crafting>
      </skillRequirements>
      <recipeUsers>
        <li>ElectricTailoringBench</li>
        <li>HandTailoringBench</li>
      </recipeUsers>
    </recipeMaker>
  </ThingDef>

  <!-- House Telvanni Cephalopod Helmet -->
  <ThingDef ParentName="ArmorMakeableBase">
    <defName>Apparel_HouseTelvanniCephalopodHelmet</defName>
    <label>House Telvanni Cephalopod helmet</label>
    <description>The distinctive cephalopod-shaped helmet worn by House Telvanni guards. This unique piece of headgear is both intimidating and practical, designed to protect the heads of those who serve the sorcerer-lords of House Telvanni. Its tentacle-like protrusions are not merely decorative but serve as magical conduits.</description>
    <graphicData>
      <texPath>Things/Pawn/Humanlike/Apparel/GreatHouses/Telvanni/TelvanniCephalopodHelm</texPath>
      <graphicClass>Graphic_Single</graphicClass>
      <shaderType>CutoutComplex</shaderType>
    </graphicData>
    <costStuffCount>80</costStuffCount>
    <stuffCategories>
      <li>Metallic</li>
      <li>Woody</li>
    </stuffCategories>
    <thingCategories>
      <li>ApparelArmor</li>
    </thingCategories>
    <statBases>
      <WorkToMake>12000</WorkToMake>
      <MaxHitPoints>140</MaxHitPoints>
      <Mass>3.0</Mass>
      <Flammability>0.4</Flammability>
      <ArmorRating_Sharp>0.75</ArmorRating_Sharp>
      <ArmorRating_Blunt>0.40</ArmorRating_Blunt>
      <ArmorRating_Heat>0.50</ArmorRating_Heat>
      <Insulation_Cold>4</Insulation_Cold>
      <Insulation_Heat>6</Insulation_Heat>
      <EquipDelay>4</EquipDelay>
    </statBases>
    <equippedStatOffsets>
      <PsychicSensitivity>0.12</PsychicSensitivity>
      <ResearchSpeed>0.08</ResearchSpeed>
      <SocialImpact>0.15</SocialImpact>
      <MentalBreakThreshold>-0.05</MentalBreakThreshold>
    </equippedStatOffsets>
    <apparel>
      <bodyPartGroups>
        <li>UpperHead</li>
        <li>FullHead</li>
      </bodyPartGroups>
      <wornGraphicPath>Things/Pawn/Humanlike/Apparel/GreatHouses/Telvanni/TelvanniCephalopodHelm</wornGraphicPath>
      <layers>
        <li>Overhead</li>
      </layers>
      <tags>
        <li>IndustrialMilitaryBasic</li>
        <li>HouseTelvanni</li>
        <li>TelvanniGuard</li>
      </tags>
      <defaultOutfitTags>
        <li>Soldier</li>
      </defaultOutfitTags>
    </apparel>
    <recipeMaker>
      <unfinishedThingDef>UnfinishedMetallicTechArmor</unfinishedThingDef>
      <researchPrerequisite>PlateArmor</researchPrerequisite>
      <skillRequirements>
        <Crafting>7</Crafting>
      </skillRequirements>
      <recipeUsers Inherit="False">
        <li>ElectricSmithy</li>
        <li>FueledSmithy</li>
      </recipeUsers>
    </recipeMaker>
  </ThingDef>

  <!-- House Indoril Ceremonial Armor -->
  <ThingDef ParentName="ArmorMakeableBase">
    <defName>Apparel_HouseIndorilArmor</defName>
    <label>House Indoril ceremonial armor</label>
    <description>Sacred armor worn by House Indoril, the devout temple guardians. This ornate armor combines protective function with religious ceremony, featuring blessed materials and sacred symbols that mark the wearer as a defender of the faith.</description>
    <graphicData>
      <texPath>Things/Pawn/Humanlike/Apparel/GreatHouses/Indoril/Indoril</texPath>
      <graphicClass>Graphic_Single</graphicClass>
    </graphicData>
    <costStuffCount>135</costStuffCount>
    <stuffCategories>
      <li>Metallic</li>
    </stuffCategories>
    <thingCategories>
      <li>ApparelArmor</li>
    </thingCategories>
    <statBases>
      <WorkToMake>24000</WorkToMake>
      <MaxHitPoints>310</MaxHitPoints>
      <Mass>14</Mass>
      <Flammability>0.3</Flammability>
      <ArmorRating_Sharp>0.78</ArmorRating_Sharp>
      <ArmorRating_Blunt>0.40</ArmorRating_Blunt>
      <ArmorRating_Heat>0.48</ArmorRating_Heat>
      <Insulation_Cold>11</Insulation_Cold>
      <Insulation_Heat>4</Insulation_Heat>
      <EquipDelay>12</EquipDelay>
    </statBases>
    <equippedStatOffsets>
      <MoveSpeed>-0.07</MoveSpeed>
      <WorkSpeedGlobal>-0.07</WorkSpeedGlobal>
      <SocialImpact>0.15</SocialImpact>
      <MentalBreakThreshold>-0.08</MentalBreakThreshold>
    </equippedStatOffsets>
    <apparel>
      <bodyPartGroups>
        <li>Torso</li>
        <li>Neck</li>
        <li>Shoulders</li>
        <li>Arms</li>
        <li>Legs</li>
      </bodyPartGroups>
      <wornGraphicPath>Things/Pawn/Humanlike/Apparel/GreatHouses/Indoril/Indoril</wornGraphicPath>
      <layers>
        <li>Middle</li>
      </layers>
      <tags>
        <li>IndustrialMilitaryAdvanced</li>
        <li>HouseIndoril</li>
      </tags>
      <defaultOutfitTags>
        <li>Soldier</li>
      </defaultOutfitTags>
    </apparel>
    <recipeMaker>
      <unfinishedThingDef>UnfinishedMetallicTechArmor</unfinishedThingDef>
      <researchPrerequisite>PlateArmor</researchPrerequisite>
      <skillRequirements>
        <Crafting>8</Crafting>
      </skillRequirements>
      <recipeUsers Inherit="False">
        <li>ElectricSmithy</li>
        <li>FueledSmithy</li>
      </recipeUsers>
    </recipeMaker>
  </ThingDef>

  <!-- House Dres Slaver Garments -->
  <ThingDef ParentName="ApparelMakeableBase">
    <defName>Apparel_HouseDresGarments</defName>
    <label>House Dres garments</label>
    <description>Practical garments worn by House Dres, the agrarian slaveholders of southern Morrowind. These sturdy clothes are designed for overseeing plantation work while projecting the authority of the slave-owning caste.</description>
    <graphicData>
      <texPath>Things/Pawn/Humanlike/Apparel/GreatHouses/Dres/Dres</texPath>
      <graphicClass>Graphic_Single</graphicClass>
    </graphicData>
    <costStuffCount>70</costStuffCount>
    <stuffCategories>
      <li>Fabric</li>
      <li>Leathery</li>
    </stuffCategories>
    <thingCategories>
      <li>Apparel</li>
    </thingCategories>
    <statBases>
      <WorkToMake>6000</WorkToMake>
      <MaxHitPoints>125</MaxHitPoints>
      <Mass>2.8</Mass>
      <Flammability>0.9</Flammability>
      <ArmorRating_Sharp>0.15</ArmorRating_Sharp>
      <ArmorRating_Blunt>0.08</ArmorRating_Blunt>
      <ArmorRating_Heat>0.50</ArmorRating_Heat>
      <Insulation_Cold>14</Insulation_Cold>
      <Insulation_Heat>18</Insulation_Heat>
      <EquipDelay>3</EquipDelay>
    </statBases>
    <equippedStatOffsets>
      <WorkSpeedGlobal>0.06</WorkSpeedGlobal>
      <PlantWorkSpeed>0.12</PlantWorkSpeed>
      <SocialImpact>0.10</SocialImpact>
      <ArrestSuccessChance>0.08</ArrestSuccessChance>
    </equippedStatOffsets>
    <apparel>
      <bodyPartGroups>
        <li>Torso</li>
        <li>Shoulders</li>
        <li>Arms</li>
        <li>Legs</li>
      </bodyPartGroups>
      <wornGraphicPath>Things/Pawn/Humanlike/Apparel/GreatHouses/Dres/Dres</wornGraphicPath>
      <layers>
        <li>Middle</li>
      </layers>
      <tags>
        <li>HouseDres</li>
      </tags>
      <defaultOutfitTags>
        <li>Worker</li>
      </defaultOutfitTags>
    </apparel>
    <recipeMaker>
      <researchPrerequisite>ComplexClothing</researchPrerequisite>
      <skillRequirements>
        <Crafting>4</Crafting>
      </skillRequirements>
      <recipeUsers>
        <li>ElectricTailoringBench</li>
        <li>HandTailoringBench</li>
      </recipeUsers>
    </recipeMaker>
  </ThingDef>

</Defs>