<?xml version="1.0" encoding="utf-8"?>
<Defs>

  <!-- Dwemeri Crossbow -->
  <ThingDef ParentName="BaseWeaponNeolithic">
    <defName>Weapon_DwemeriCrossbow</defName>
    <label>Dwemeri crossbow</label>
    <description>A masterwork crossbow incorporating Dwemer engineering principles. The mechanical loading system reduces draw time while maintaining exceptional accuracy and power. Intricate bronze mechanisms automatically adjust for wind and distance, making this weapon deadly in the hands of skilled marksmen.</description>
    <graphicData>
      <texPath>Things/Item/Equipment/WeaponRanged/DwemeriCrossbow</texPath>
      <graphicClass>Graphic_Single</graphicClass>
    </graphicData>
    <uiIconPath>Things/Item/Equipment/WeaponRanged/DwemeriCrossbow</uiIconPath>
    <soundInteract>Interact_Rifle</soundInteract>
    <costList>
      <DwarvenMetalIngot>3</DwarvenMetalIngot>
      <WoodLog>25</WoodLog>
      <ComponentIndustrial>2</ComponentIndustrial>
    </costList>
    <statBases>
      <WorkToMake>15000</WorkToMake>
      <Mass>2.8</Mass>
      <AccuracyTouch>0.75</AccuracyTouch>
      <AccuracyShort>0.85</AccuracyShort>
      <AccuracyMedium>0.75</AccuracyMedium>
      <AccuracyLong>0.65</AccuracyLong>
      <RangedWeapon_Cooldown>2.8</RangedWeapon_Cooldown>
    </statBases>
    <recipeMaker>
      <researchPrerequisite>DwemerCrafting</researchPrerequisite>
      <skillRequirements>
        <Crafting>8</Crafting>
      </skillRequirements>
      <workSpeedStat>GeneralLaborSpeed</workSpeedStat>
      <workSkill>Crafting</workSkill>
      <effectWorking>Smith</effectWorking>
      <soundWorking>Recipe_Smith</soundWorking>
      <recipeUsers>
        <li>CraftingSpot</li>
        <li>Smith</li>
      </recipeUsers>
      <unfinishedThingDef>UnfinishedGun</unfinishedThingDef>
    </recipeMaker>
    <weaponTags>
      <li>DwemeriWeapon</li>
      <li>MedievalRanged</li>
    </weaponTags>
    <thingCategories>
      <li>WeaponsRanged</li>
    </thingCategories>
    <verbs>
      <li>
        <verbClass>Verb_Shoot</verbClass>
        <hasStandardCommand>true</hasStandardCommand>
        <defaultProjectile>Arrow_Steel</defaultProjectile>
        <warmupTime>2.2</warmupTime>
        <range>32</range>
        <soundCast>Bow_Large</soundCast>
        <soundCastTail>GunTail_Light</soundCastTail>
        <muzzleFlashScale>9</muzzleFlashScale>
      </li>
    </verbs>
    <tools>
      <li>
        <label>stock</label>
        <capacities>
          <li>Blunt</li>
        </capacities>
        <power>9</power>
        <cooldownTime>2</cooldownTime>
      </li>
    </tools>
  </ThingDef>

  <!-- Dwemeri War Hammer -->
  <ThingDef ParentName="BaseMeleeWeapon_Sharp_Quality">
    <defName>MeleeWeapon_DwemeriWarHammer</defName>
    <label>Dwemeri war hammer</label>
    <description>A massive two-handed war hammer forged from dwarven metal and incorporating steam-powered mechanisms. When swung, internal pistons activate to multiply the impact force, making this weapon capable of crushing even the heaviest armor. The bronze head is inscribed with complex geometric patterns that seem to pulse with inner energy.</description>
    <graphicData>
      <texPath>Things/Item/Equipment/WeaponMelee/DwemeriWarHammer</texPath>
      <graphicClass>Graphic_Single</graphicClass>
    </graphicData>
    <uiIconPath>Things/Item/Equipment/WeaponMelee/DwemeriWarHammer</uiIconPath>
    <costStuffCount>80</costStuffCount>
    <stuffCategories>
      <li>Metallic</li>
    </stuffCategories>
    <costList>
      <DwarvenMetalIngot>4</DwarvenMetalIngot>
      <ComponentIndustrial>1</ComponentIndustrial>
    </costList>
    <statBases>
      <WorkToMake>18000</WorkToMake>
      <Mass>4.2</Mass>
    </statBases>
    <recipeMaker>
      <researchPrerequisite>DwemerCrafting</researchPrerequisite>
      <skillRequirements>
        <Crafting>10</Crafting>
      </skillRequirements>
      <recipeUsers>
        <li>FueledSmithy</li>
        <li>ElectricSmithy</li>
      </recipeUsers>
    </recipeMaker>
    <weaponTags>
      <li>DwemeriWeapon</li>
      <li>MedievalMeleeAdvanced</li>
    </weaponTags>
    <thingCategories>
      <li>WeaponsMelee</li>
    </thingCategories>
    <equippedStatOffsets>
      <MoveSpeed>-0.15</MoveSpeed>
      <MeleeHitChance>-0.10</MeleeHitChance>
    </equippedStatOffsets>
    <tools>
      <li>
        <label>head</label>
        <capacities>
          <li>Blunt</li>
        </capacities>
        <power>28</power>
        <cooldownTime>3.5</cooldownTime>
        <armorPenetration>0.45</armorPenetration>
        <chanceFactor>1.33</chanceFactor>
      </li>
      <li>
        <label>handle</label>
        <capacities>
          <li>Blunt</li>
        </capacities>
        <power>12</power>
        <cooldownTime>2.2</cooldownTime>
      </li>
    </tools>
  </ThingDef>

  <!-- Dwemeri Precision Blade -->
  <ThingDef ParentName="BaseMeleeWeapon_Sharp_Quality">
    <defName>MeleeWeapon_DwemeriPrecisionBlade</defName>
    <label>Dwemeri precision blade</label>
    <description>An elegant sword forged from the finest dwarven metal, incorporating microscopic gears and springs that enhance the wielder's precision and speed. The blade's edge is maintained at a molecular level by tiny mechanical systems, ensuring it never dulls. The geometric patterns etched into the fuller are not merely decorative - they channel kinetic energy to increase cutting power.</description>
    <graphicData>
      <texPath>Things/Item/Equipment/WeaponMelee/DwemeriPrecisionBlade</texPath>
      <graphicClass>Graphic_Single</graphicClass>
    </graphicData>
    <uiIconPath>Things/Item/Equipment/WeaponMelee/DwemeriPrecisionBlade</uiIconPath>
    <costStuffCount>65</costStuffCount>
    <stuffCategories>
      <li>Metallic</li>
    </stuffCategories>
    <costList>
      <DwarvenMetalIngot>3</DwarvenMetalIngot>
      <ComponentIndustrial>1</ComponentIndustrial>
      <Gold>8</Gold>
    </costList>
    <statBases>
      <WorkToMake>22000</WorkToMake>
      <Mass>1.8</Mass>
    </statBases>
    <recipeMaker>
      <researchPrerequisite>DwemerEngineering</researchPrerequisite>
      <skillRequirements>
        <Crafting>12</Crafting>
      </skillRequirements>
      <recipeUsers>
        <li>FueledSmithy</li>
        <li>ElectricSmithy</li>
      </recipeUsers>
    </recipeMaker>
    <weaponTags>
      <li>DwemeriWeapon</li>
      <li>MedievalMeleeAdvanced</li>
    </weaponTags>
    <thingCategories>
      <li>WeaponsMelee</li>
    </thingCategories>
    <equippedStatOffsets>
      <MoveSpeed>0.05</MoveSpeed>
      <MeleeHitChance>0.15</MeleeHitChance>
      <MeleeDodgeChance>0.08</MeleeDodgeChance>
    </equippedStatOffsets>
    <tools>
      <li>
        <label>point</label>
        <capacities>
          <li>Stab</li>
        </capacities>
        <power>18</power>
        <cooldownTime>1.8</cooldownTime>
        <armorPenetration>0.35</armorPenetration>
        <chanceFactor>1.40</chanceFactor>
      </li>
      <li>
        <label>edge</label>
        <capacities>
          <li>Cut</li>
        </capacities>
        <power>22</power>
        <cooldownTime>2.0</cooldownTime>
        <armorPenetration>0.25</armorPenetration>
        <chanceFactor>1.30</chanceFactor>
      </li>
      <li>
        <label>pommel</label>
        <capacities>
          <li>Blunt</li>
        </capacities>
        <power>9</power>
        <cooldownTime>1.5</cooldownTime>
      </li>
    </tools>
  </ThingDef>

</Defs>