<?xml version="1.0" encoding="utf-8"?>
<BiomeDefs>

  <!-- Ashlands - Volcanic wasteland with ash storms -->
  <BiomeDef>
    <defName>Ashlands</defName>
    <label>ashlands</label>
    <description>A desolate volcanic wasteland covered in ash and hostile to most life. The air is thick with volcanic particles, and violent ash storms regularly sweep across the barren landscape. Despite the harsh conditions, some hardy creatures and volcanic plants have adapted to thrive here.</description>
    <workerClass>BiomeWorker_Desert</workerClass>
    <canAutoChoose>true</canAutoChoose>
    <animalDensity>0.3</animalDensity>
    <plantDensity>0.15</plantDensity>
    <settlementSelectionWeight>0.1</settlementSelectionWeight>
    <movementDifficulty>1.2</movementDifficulty>
    <texture>World/Biomes/Desert</texture>
    <wildPlantRegrowDays>40</wildPlantRegrowDays>
    <soundsAmbient>
      <li>Ambient_Wind_Desolate</li>
    </soundsAmbient>
    <baseWeatherCommonalities>
      <Clear>18</Clear>
      <Fog>1</Fog>
      <Rain>2</Rain>
      <DryThunderstorm>3</DryThunderstorm>
      <SnowGentle>0</SnowGentle>
      <SnowHard>0</SnowHard>
    </baseWeatherCommonalities>
    <wildAnimals>
      <Alit>0.3</Alit>
      <Kagouti>0.2</Kagouti>
      <NixHound>0.15</NixHound>
      <Shalk>0.1</Shalk>
    </wildAnimals>
    <wildPlants>
      <PlantAshYam>0.5</PlantAshYam>
      <PlantFirePetal>0.3</PlantFirePetal>
    </wildPlants>
    <terrainsByFertility>
      <li>
        <terrain>Sand</terrain>
        <min>-999</min>
        <max>0.87</max>
      </li>
      <li>
        <terrain>Soil</terrain>
        <min>0.87</min>
        <max>999</max>
      </li>
    </terrainsByFertility>
    <terrainPatchMakers>
      <li>
        <perlinFrequency>0.035</perlinFrequency>
        <thresholds>
          <li>
            <terrain>Sand</terrain>
            <min>0.15</min>
            <max>999</max>
          </li>
        </thresholds>
      </li>
    </terrainPatchMakers>
  </BiomeDef>

  <!-- Bitter Coast - Swampy coastland with fungal forests -->
  <BiomeDef>
    <defName>BitterCoast</defName>
    <label>bitter coast</label>
    <description>A humid, misty swampland where strange fungal trees grow in twisted formations. The air is thick with spores and moisture, creating an alien landscape dominated by towering mushrooms and brackish waters. This ecosystem supports unique flora and fauna adapted to the perpetually damp conditions.</description>
    <workerClass>BiomeWorker_Swamp</workerClass>
    <canAutoChoose>true</canAutoChoose>
    <animalDensity>0.8</animalDensity>
    <plantDensity>0.9</plantDensity>
    <settlementSelectionWeight>0.7</settlementSelectionWeight>
    <movementDifficulty>1.3</movementDifficulty>
    <texture>World/Biomes/Swamp</texture>
    <wildPlantRegrowDays>15</wildPlantRegrowDays>
    <soundsAmbient>
      <li>Ambient_Wind_Swamp</li>
    </soundsAmbient>
    <baseWeatherCommonalities>
      <Clear>8</Clear>
      <Fog>8</Fog>
      <Rain>12</Rain>
      <DryThunderstorm>1</DryThunderstorm>
      <RainyThunderstorm>4</RainyThunderstorm>
      <SnowGentle>0</SnowGentle>
      <SnowHard>0</SnowHard>
    </baseWeatherCommonalities>
    <wildAnimals>
      <Guar>0.4</Guar>
      <BettyNetch>0.3</BettyNetch>
      <NixHound>0.2</NixHound>
      <KwamaWorker>0.1</KwamaWorker>
    </wildAnimals>
    <wildPlants>
      <PlantMarshmerrow>0.8</PlantMarshmerrow>
      <PlantSaltrice>0.4</PlantSaltrice>
      <PlantComberry>0.3</PlantComberry>
    </wildPlants>
    <terrainsByFertility>
      <li>
        <terrain>Marsh</terrain>
        <min>-999</min>
        <max>0.6</max>
      </li>
      <li>
        <terrain>Mud</terrain>
        <min>0.6</min>
        <max>0.87</max>
      </li>
      <li>
        <terrain>Soil</terrain>
        <min>0.87</min>
        <max>999</max>
      </li>
    </terrainsByFertility>
    <terrainPatchMakers>
      <li>
        <perlinFrequency>0.025</perlinFrequency>
        <thresholds>
          <li>
            <terrain>WaterShallow</terrain>
            <min>0.1</min>
            <max>0.3</max>
          </li>
        </thresholds>
      </li>
    </terrainPatchMakers>
  </BiomeDef>

  <!-- Grazelands - Fertile grasslands -->
  <BiomeDef>
    <defName>Grazelands</defName>
    <label>grazelands</label>
    <description>Rolling grasslands dotted with grazing herds and colorful wildflowers. This fertile region enjoys moderate weather and supports abundant wildlife, making it ideal for agriculture and settlement. The landscape is characterized by gentle hills and vast open meadows.</description>
    <workerClass>BiomeWorker_Grassland</workerClass>
    <canAutoChoose>true</canAutoChoose>
    <animalDensity>1.2</animalDensity>
    <plantDensity>0.85</plantDensity>
    <settlementSelectionWeight>1.5</settlementSelectionWeight>
    <movementDifficulty>1.0</movementDifficulty>
    <texture>World/Biomes/Grassland</texture>
    <wildPlantRegrowDays>20</wildPlantRegrowDays>
    <soundsAmbient>
      <li>Ambient_Wind_Calm</li>
    </soundsAmbient>
    <baseWeatherCommonalities>
      <Clear>12</Clear>
      <Fog>1</Fog>
      <Rain>6</Rain>
      <DryThunderstorm>1</DryThunderstorm>
      <RainyThunderstorm>2</RainyThunderstorm>
      <SnowGentle>2</SnowGentle>
      <SnowHard>1</SnowHard>
    </baseWeatherCommonalities>
    <wildAnimals>
      <Guar>0.8</Guar>
      <BettyNetch>0.6</BettyNetch>
      <NixHound>0.3</NixHound>
      <Kagouti>0.2</Kagouti>
    </wildAnimals>
    <wildPlants>
      <PlantWickwheat>0.6</PlantWickwheat>
      <PlantSaltrice>0.5</PlantSaltrice>
      <PlantGoldKanet>0.3</PlantGoldKanet>
    </wildPlants>
    <terrainsByFertility>
      <li>
        <terrain>Soil</terrain>
        <min>-999</min>
        <max>0.87</max>
      </li>
      <li>
        <terrain>SoilRich</terrain>
        <min>0.87</min>
        <max>999</max>
      </li>
    </terrainsByFertility>
    <terrainPatchMakers>
      <li>
        <perlinFrequency>0.04</perlinFrequency>
        <thresholds>
          <li>
            <terrain>SoilRich</terrain>
            <min>0.3</min>
            <max>999</max>
          </li>
        </thresholds>
      </li>
    </terrainPatchMakers>
  </BiomeDef>

  <!-- West Gash - Rocky highlands and river valleys -->
  <BiomeDef>
    <defName>WestGash</defName>
    <label>west gash</label>
    <description>A region of rocky highlands cut by river valleys and dotted with ancient ruins. The terrain is rugged and varied, with stone formations, flowing streams, and patches of hardy vegetation that cling to the rocky soil. This landscape offers both shelter and challenges to those who traverse it.</description>
    <workerClass>BiomeWorker_Mountain</workerClass>
    <canAutoChoose>true</canAutoChoose>
    <animalDensity>0.6</animalDensity>
    <plantDensity>0.5</plantDensity>
    <settlementSelectionWeight>0.8</settlementSelectionWeight>
    <movementDifficulty>1.4</movementDifficulty>
    <texture>World/Biomes/Hills</texture>
    <wildPlantRegrowDays>25</wildPlantRegrowDays>
    <soundsAmbient>
      <li>Ambient_Wind_Hills</li>
    </soundsAmbient>
    <baseWeatherCommonalities>
      <Clear>10</Clear>
      <Fog>2</Fog>
      <Rain>8</Rain>
      <DryThunderstorm>2</DryThunderstorm>
      <RainyThunderstorm>3</RainyThunderstorm>
      <SnowGentle>3</SnowGentle>
      <SnowHard>2</SnowHard>
    </baseWeatherCommonalities>
    <wildAnimals>
      <Kagouti>0.4</Kagouti>
      <Alit>0.3</Alit>
      <NixHound>0.25</NixHound>
      <Shalk>0.15</Shalk>
    </wildAnimals>
    <wildPlants>
      <PlantWickwheat>0.4</PlantWickwheat>
      <PlantSaltrice>0.3</PlantSaltrice>
      <PlantHackleLoLeaf>0.3</PlantHackleLoLeaf>
    </wildPlants>
    <terrainsByFertility>
      <li>
        <terrain>Gravel</terrain>
        <min>-999</min>
        <max>0.4</max>
      </li>
      <li>
        <terrain>Soil</terrain>
        <min>0.4</min>
        <max>0.87</max>
      </li>
      <li>
        <terrain>SoilRich</terrain>
        <min>0.87</min>
        <max>999</max>
      </li>
    </terrainsByFertility>
    <terrainPatchMakers>
      <li>
        <perlinFrequency>0.045</perlinFrequency>
        <thresholds>
          <li>
            <terrain>WaterShallow</terrain>
            <min>0.05</min>
            <max>0.15</max>
          </li>
        </thresholds>
      </li>
    </terrainPatchMakers>
  </BiomeDef>

  <!-- Molag Amur - Lava flows and harsh ashlands -->
  <BiomeDef>
    <defName>MolagAmur</defName>
    <label>molag amur</label>
    <description>The most hostile region of Morrowind, characterized by active lava flows, sulfurous air, and extreme heat. This volcanic wasteland is nearly devoid of life except for the most adapted creatures and heat-resistant plants. The landscape constantly shifts as new lava flows reshape the terrain.</description>
    <workerClass>BiomeWorker_Desert</workerClass>
    <canAutoChoose>true</canAutoChoose>
    <animalDensity>0.1</animalDensity>
    <plantDensity>0.05</plantDensity>
    <settlementSelectionWeight>0.05</settlementSelectionWeight>
    <movementDifficulty>1.8</movementDifficulty>
    <texture>World/Biomes/Desert</texture>
    <wildPlantRegrowDays>60</wildPlantRegrowDays>
    <soundsAmbient>
      <li>Ambient_Wind_Desolate</li>
    </soundsAmbient>
    <baseWeatherCommonalities>
      <Clear>20</Clear>
      <Fog>0</Fog>
      <Rain>1</Rain>
      <DryThunderstorm>4</DryThunderstorm>
      <SnowGentle>0</SnowGentle>
      <SnowHard>0</SnowHard>
    </baseWeatherCommonalities>
    <wildAnimals>
      <FlameAtronach>0.1</FlameAtronach>
      <Alit>0.05</Alit>
      <Shalk>0.05</Shalk>
    </wildAnimals>
    <wildPlants>
      <PlantAshYam>0.2</PlantAshYam>
      <PlantFirePetal>0.3</PlantFirePetal>
    </wildPlants>
    <terrainsByFertility>
      <li>
        <terrain>Sand</terrain>
        <min>-999</min>
        <max>0.5</max>
      </li>
      <li>
        <terrain>Gravel</terrain>
        <min>0.5</min>
        <max>999</max>
      </li>
    </terrainsByFertility>
    <terrainPatchMakers>
      <li>
        <perlinFrequency>0.03</perlinFrequency>
        <thresholds>
          <li>
            <terrain>Lava</terrain>
            <min>0.05</min>
            <max>0.2</max>
          </li>
        </thresholds>
      </li>
    </terrainPatchMakers>
  </BiomeDef>

</BiomeDefs>